setup.py
ppworkflows/__init__.py
ppworkflows/parallel.py
ppworkflows/tasks.py
ppworkflows.egg-info/PKG-INFO
ppworkflows.egg-info/SOURCES.txt
ppworkflows.egg-info/dependency_links.txt
ppworkflows.egg-info/not-zip-safe
ppworkflows.egg-info/top_level.txt