Metadata-Version: 1.0
Name: ppworkflows
Version: 0.1.5
Summary: Execute data-driven task-based workflows in parallel with Python.
Home-page: http://github.com/markus1978/ppworkflows
Author: Markus Scheidgen
Author-email: markus.scheidgen@gmail.com
License: MIT
Platform: UNKNOWN
